{
	"partitions" : [
		{
			"name" : "Top",
			"pins" : [
				{
					"name" : "rom_out[0]",
					"strict" : false
				},
				{
					"name" : "rom_out[1]",
					"strict" : false
				},
				{
					"name" : "rom_out[2]",
					"strict" : false
				},
				{
					"name" : "rom_out[3]",
					"strict" : false
				},
				{
					"name" : "rom_out[4]",
					"strict" : false
				},
				{
					"name" : "rom_out[5]",
					"strict" : false
				},
				{
					"name" : "rom_out[6]",
					"strict" : false
				},
				{
					"name" : "rom_out[7]",
					"strict" : false
				},
				{
					"name" : "rom_out[8]",
					"strict" : false
				},
				{
					"name" : "rom_out[9]",
					"strict" : false
				},
				{
					"name" : "rom_out[10]",
					"strict" : false
				},
				{
					"name" : "rom_out[11]",
					"strict" : false
				},
				{
					"name" : "rom_out[12]",
					"strict" : false
				},
				{
					"name" : "rom_out[13]",
					"strict" : false
				},
				{
					"name" : "rom_out[14]",
					"strict" : false
				},
				{
					"name" : "rom_out[15]",
					"strict" : false
				},
				{
					"name" : "source_imag[0]",
					"strict" : false
				},
				{
					"name" : "source_imag[1]",
					"strict" : false
				},
				{
					"name" : "source_imag[2]",
					"strict" : false
				},
				{
					"name" : "source_imag[3]",
					"strict" : false
				},
				{
					"name" : "source_imag[4]",
					"strict" : false
				},
				{
					"name" : "source_imag[5]",
					"strict" : false
				},
				{
					"name" : "source_imag[6]",
					"strict" : false
				},
				{
					"name" : "source_imag[7]",
					"strict" : false
				},
				{
					"name" : "source_imag[8]",
					"strict" : false
				},
				{
					"name" : "source_imag[9]",
					"strict" : false
				},
				{
					"name" : "source_imag[10]",
					"strict" : false
				},
				{
					"name" : "source_imag[11]",
					"strict" : false
				},
				{
					"name" : "source_imag[12]",
					"strict" : false
				},
				{
					"name" : "source_imag[13]",
					"strict" : false
				},
				{
					"name" : "source_imag[14]",
					"strict" : false
				},
				{
					"name" : "source_imag[15]",
					"strict" : false
				},
				{
					"name" : "source_real[0]",
					"strict" : false
				},
				{
					"name" : "source_real[1]",
					"strict" : false
				},
				{
					"name" : "source_real[2]",
					"strict" : false
				},
				{
					"name" : "source_real[3]",
					"strict" : false
				},
				{
					"name" : "source_real[4]",
					"strict" : false
				},
				{
					"name" : "source_real[5]",
					"strict" : false
				},
				{
					"name" : "source_real[6]",
					"strict" : false
				},
				{
					"name" : "source_real[7]",
					"strict" : false
				},
				{
					"name" : "source_real[8]",
					"strict" : false
				},
				{
					"name" : "source_real[9]",
					"strict" : false
				},
				{
					"name" : "source_real[10]",
					"strict" : false
				},
				{
					"name" : "source_real[11]",
					"strict" : false
				},
				{
					"name" : "source_real[12]",
					"strict" : false
				},
				{
					"name" : "source_real[13]",
					"strict" : false
				},
				{
					"name" : "source_real[14]",
					"strict" : false
				},
				{
					"name" : "source_real[15]",
					"strict" : false
				},
				{
					"name" : "sink_sop_out",
					"strict" : false
				},
				{
					"name" : "sink_eop_out",
					"strict" : false
				},
				{
					"name" : "sink_valid_out",
					"strict" : false
				},
				{
					"name" : "CLK",
					"strict" : false
				},
				{
					"name" : "RESET",
					"strict" : false
				},
				{
					"name" : "trigger_in",
					"strict" : false
				}
			]
		}
	]
}